.gitignore
CHANGELOG.md
LICENSE
MANIFEST.in
README.md
dev.requirements.txt
format.sh
setup.py
test.py
.github/workflows/ci.yml
.github/workflows/dev.yml
.github/workflows/main.yml
.github/workflows/release.yml
.vscode/settings.json
slugify/__init__.py
slugify/__main__.py
slugify/__version__.py
slugify/slugify.py
slugify/special.py
typed_slugify.egg-info/PKG-INFO
typed_slugify.egg-info/SOURCES.txt
typed_slugify.egg-info/dependency_links.txt
typed_slugify.egg-info/entry_points.txt
typed_slugify.egg-info/not-zip-safe
typed_slugify.egg-info/requires.txt
typed_slugify.egg-info/top_level.txt