Metadata-Version: 2.1
Name: typed-slugify
Version: 8.0.1
Summary: A Python slugify application that also handles Unicode
Home-page: https://github.com/jmelahman/typed-slugify
Author: Jamison Lahman
Author-email: jamison@lahman.dev
License: MIT
Classifier: Development Status :: 5 - Production/Stable
Classifier: Intended Audience :: Developers
Classifier: Natural Language :: English
Classifier: License :: OSI Approved :: MIT License
Classifier: Programming Language :: Python
Classifier: Programming Language :: Python :: 3
Classifier: Programming Language :: Python :: 3.7
Classifier: Programming Language :: Python :: 3.8
Classifier: Programming Language :: Python :: 3.9
Classifier: Programming Language :: Python :: 3.10
Classifier: Programming Language :: Python :: 3.11
Requires-Python: >=3.7
Provides-Extra: unidecode
License-File: LICENSE
